senstream/__init__.py
senstream/alert_manager.py
senstream/report_manager.py
senstream/resensys.py
senstream/senimax.py
senstream/senscope.py
senstream/senspot.py
senstream/stream_builder.py
senstream-1.4.23.dist-info/METADATA
senstream-1.4.23.dist-info/WHEEL
senstream-1.4.23.dist-info/top_level.txt
senstream-1.4.23.dist-info/RECORD
