Metadata-Version: 2.1
Name: senstream
Version: 1.4.23
Summary: Python package for managing and interacting with Resensys SenSpots.
Home-page: UNKNOWN
Author: Resensys (Tom Wade)
Author-email: <thomas.wade@resensys.com>
License: UNKNOWN
Keywords: python,stream,senspot,resensys,time series
Platform: UNKNOWN
Classifier: Development Status :: 1 - Planning
Classifier: Intended Audience :: Developers
Classifier: Programming Language :: Python :: 3
Classifier: Operating System :: Unix
Classifier: Operating System :: MacOS :: MacOS X
Classifier: Operating System :: Microsoft :: Windows
Requires-Dist: mysql-connector-python (==8.0.25)
Requires-Dist: pymysql
Requires-Dist: numpy
Requires-Dist: pandas
Requires-Dist: datetime
Requires-Dist: requests
Requires-Dist: progress
